python_billomat-0.5.2.dist-info/metadata.json
python_billomat-0.5.2.dist-info/WHEEL
python_billomat-0.5.2.dist-info/DESCRIPTION.rst
python_billomat-0.5.2.dist-info/METADATA
python_billomat-0.5.2.dist-info/top_level.txt
python_billomat-0.5.2.dist-info/RECORD
pybillomat/reminder_items.py
pybillomat/reminders.py
pybillomat/recurring_email_receivers.py
pybillomat/errors.py
pybillomat/http.py
pybillomat/article_properties.py
pybillomat/contacts.py
pybillomat/email_templates.py
pybillomat/credit_note_tags.py
pybillomat/reminder_texts.py
pybillomat/credit_notes.py
pybillomat/credit_note_items.py
pybillomat/invoice_tags.py
pybillomat/invoices.py
pybillomat/client_properties.py
pybillomat/reminder_tags.py
pybillomat/invoice_items.py
pybillomat/suppliers.py
pybillomat/invoice_payments.py
pybillomat/articles.py
pybillomat/recurrings.py
pybillomat/article_tags.py
pybillomat/_items_base.py
pybillomat/__init__.py
pybillomat/recurring_items.py
pybillomat/client_tags.py
pybillomat/recurring_tags.py
pybillomat/clients.py
