Metadata-Version: 2.0
Name: python-billomat
Version: 0.5.2
Summary: Python Billomat API Client Library
Home-page: https://github.com/gerold-penz/python-billomat
Author: Gerold Penz
Author-email: gerold@halvar.at
License: UNKNOWN
Download-URL: https://github.com/gerold-penz/python-billomat/raw/master/dist/python-billomat-0.5.2.tar.gz
Keywords: Billomat,Client,API,Data Interchange,Google App Engine,REST Api
Platform: UNKNOWN
Classifier: Development Status :: 4 - Beta
Classifier: Environment :: Web Environment
Classifier: Intended Audience :: Developers
Classifier: License :: OSI Approved :: GNU Library or Lesser General Public License (LGPL)
Classifier: License :: OSI Approved :: MIT License
Classifier: Operating System :: OS Independent
Classifier: Programming Language :: Python :: 2
Classifier: Topic :: Internet :: WWW/HTTP
Classifier: Topic :: Office/Business :: Financial
Classifier: Topic :: Software Development :: Libraries :: Python Modules
Classifier: Topic :: System :: Networking
Requires-Dist: bunch
Requires-Dist: urllib3
